bbb_dlc/__init__.py
bbb_dlc/main.py
bbb_dlc/version.py
bbb_dlc/bigbluebutton_api_python/__init__.py
bbb_dlc/bigbluebutton_api_python/bigbluebutton.py
bbb_dlc/bigbluebutton_api_python/core/__init__.py
bbb_dlc/bigbluebutton_api_python/core/apimethod.py
bbb_dlc/bigbluebutton_api_python/core/attendee.py
bbb_dlc/bigbluebutton_api_python/core/meeting.py
bbb_dlc/bigbluebutton_api_python/core/meetinginfo.py
bbb_dlc/bigbluebutton_api_python/core/metaData.py
bbb_dlc/bigbluebutton_api_python/core/record.py
bbb_dlc/bigbluebutton_api_python/exception/__init__.py
bbb_dlc/bigbluebutton_api_python/exception/bbbexception.py
bbb_dlc/bigbluebutton_api_python/parameters/__init__.py
bbb_dlc/bigbluebutton_api_python/parameters/bbbmodule.py
bbb_dlc/bigbluebutton_api_python/responses/__init__.py
bbb_dlc/bigbluebutton_api_python/responses/apiversion.py
bbb_dlc/bigbluebutton_api_python/responses/base.py
bbb_dlc/bigbluebutton_api_python/responses/createmeeting.py
bbb_dlc/bigbluebutton_api_python/responses/deleterecordings.py
bbb_dlc/bigbluebutton_api_python/responses/endmeeting.py
bbb_dlc/bigbluebutton_api_python/responses/getmeetinginfo.py
bbb_dlc/bigbluebutton_api_python/responses/getmeetings.py
bbb_dlc/bigbluebutton_api_python/responses/getrecordings.py
bbb_dlc/bigbluebutton_api_python/responses/ismeetingrunning.py
bbb_dlc/bigbluebutton_api_python/responses/publishrecordings.py
bbb_dlc/bigbluebutton_api_python/responses/setconfigxml.py
bbb_dlc/bigbluebutton_api_python/responses/updaterecordings.py
bbb_dlc/bigbluebutton_api_python/util/__init__.py
bbb_dlc/bigbluebutton_api_python/util/urlbuilder.py
bbb_dlc-0.2.2.4.dist-info/AUTHORS
bbb_dlc-0.2.2.4.dist-info/LICENSE
bbb_dlc-0.2.2.4.dist-info/METADATA
bbb_dlc-0.2.2.4.dist-info/WHEEL
bbb_dlc-0.2.2.4.dist-info/entry_points.txt
bbb_dlc-0.2.2.4.dist-info/top_level.txt
bbb_dlc-0.2.2.4.dist-info/RECORD
