Metadata-Version: 2.1
Name: bbb-dlc
Version: 0.2.2.4
Summary: Big Blue Button Downloader that downloads a BBB lesson as MP4 video
Home-page: UNKNOWN
Author: Heracles421
License: GPL-2.0
Platform: UNKNOWN
Classifier: Development Status :: 4 - Beta
Classifier: Intended Audience :: End Users/Desktop
Classifier: License :: OSI Approved :: GNU General Public License v3 (GPLv3)
Classifier: Programming Language :: Python :: 3 :: Only
Classifier: Topic :: Education
Classifier: Topic :: Internet :: WWW/HTTP :: Indexing/Search
Classifier: Topic :: Multimedia :: Video
Classifier: Topic :: Multimedia :: Sound/Audio
Classifier: Topic :: Utilities
Requires-Python: >=3.6
License-File: LICENSE
License-File: AUTHORS
Requires-Dist: cairosvg
Requires-Dist: youtube-dl
Requires-Dist: Pillow
Requires-Dist: pathvalidate
